{
  "url": "https://api.github.com/repos/Kingsmanvn-Official/Revanced-tool/releases/83672328",
  "assets_url": "https://api.github.com/repos/Kingsmanvn-Official/Revanced-tool/releases/83672328/assets",
  "upload_url": "https://uploads.github.com/repos/Kingsmanvn-Official/Revanced-tool/releases/83672328/assets{?name,label}",
  "html_url": "https://github.com/Kingsmanvn-Official/Revanced-tool/releases/tag/1",
  "id": 83672328,
  "author": {
    "login": "github-actions[bot]",
    "id": 41898282,
    "node_id": "MDM6Qm90NDE4OTgyODI=",
    "avatar_url": "https://avatars.githubusercontent.com/in/15368?v=4",
    "gravatar_id": "",
    "url": "https://api.github.com/users/github-actions%5Bbot%5D",
    "html_url": "https://github.com/apps/github-actions",
    "followers_url": "https://api.github.com/users/github-actions%5Bbot%5D/followers",
    "following_url": "https://api.github.com/users/github-actions%5Bbot%5D/following{/other_user}",
    "gists_url": "https://api.github.com/users/github-actions%5Bbot%5D/gists{/gist_id}",
    "starred_url": "https://api.github.com/users/github-actions%5Bbot%5D/starred{/owner}{/repo}",
    "subscriptions_url": "https://api.github.com/users/github-actions%5Bbot%5D/subscriptions",
    "organizations_url": "https://api.github.com/users/github-actions%5Bbot%5D/orgs",
    "repos_url": "https://api.github.com/users/github-actions%5Bbot%5D/repos",
    "events_url": "https://api.github.com/users/github-actions%5Bbot%5D/events{/privacy}",
    "received_events_url": "https://api.github.com/users/github-actions%5Bbot%5D/received_events",
    "type": "Bot",
    "site_admin": false
  },
  "node_id": "RE_kwDOICdUDM4E_L0I",
  "tag_name": "1",
  "target_commitish": "main",
  "name": "Revanced-v17.43.36",
  "draft": false,
  "prerelease": false,
  "created_at": "2022-11-20T08:38:20Z",
  "published_at": "2022-11-20T08:49:40Z",
  "assets": [
    {
      "url": "https://api.github.com/repos/Kingsmanvn-Official/Revanced-tool/releases/assets/85325703",
      "id": 85325703,
      "node_id": "RA_kwDOICdUDM4FFfeH",
      "name": "YT-Magisk-17.43.36-arm64.Amoled.Zip",
      "label": "",
      "uploader": {
        "login": "github-actions[bot]",
        "id": 41898282,
        "node_id": "MDM6Qm90NDE4OTgyODI=",
        "avatar_url": "https://avatars.githubusercontent.com/in/15368?v=4",
        "gravatar_id": "",
        "url": "https://api.github.com/users/github-actions%5Bbot%5D",
        "html_url": "https://github.com/apps/github-actions",
        "followers_url": "https://api.github.com/users/github-actions%5Bbot%5D/followers",
        "following_url": "https://api.github.com/users/github-actions%5Bbot%5D/following{/other_user}",
        "gists_url": "https://api.github.com/users/github-actions%5Bbot%5D/gists{/gist_id}",
        "starred_url": "https://api.github.com/users/github-actions%5Bbot%5D/starred{/owner}{/repo}",
        "subscriptions_url": "https://api.github.com/users/github-actions%5Bbot%5D/subscriptions",
        "organizations_url": "https://api.github.com/users/github-actions%5Bbot%5D/orgs",
        "repos_url": "https://api.github.com/users/github-actions%5Bbot%5D/repos",
        "events_url": "https://api.github.com/users/github-actions%5Bbot%5D/events{/privacy}",
        "received_events_url": "https://api.github.com/users/github-actions%5Bbot%5D/received_events",
        "type": "Bot",
        "site_admin": false
      },
      "content_type": "binary/octet-stream",
      "state": "uploaded",
      "size": 58297012,
      "download_count": 0,
      "created_at": "2022-11-20T18:13:48Z",
      "updated_at": "2022-11-20T18:13:51Z",
      "browser_download_url": "https://github.com/Kingsmanvn-Official/Revanced-tool/releases/download/1/YT-Magisk-17.43.36-arm64.Amoled.Zip"
    },
    {
      "url": "https://api.github.com/repos/Kingsmanvn-Official/Revanced-tool/releases/assets/85325597",
      "id": 85325597,
      "node_id": "RA_kwDOICdUDM4FFfcd",
      "name": "YT-Magisk-17.43.36-arm64.Zip",
      "label": "",
      "uploader": {
        "login": "github-actions[bot]",
        "id": 41898282,
        "node_id": "MDM6Qm90NDE4OTgyODI=",
        "avatar_url": "https://avatars.githubusercontent.com/in/15368?v=4",
        "gravatar_id": "",
        "url": "https://api.github.com/users/github-actions%5Bbot%5D",
        "html_url": "https://github.com/apps/github-actions",
        "followers_url": "https://api.github.com/users/github-actions%5Bbot%5D/followers",
        "following_url": "https://api.github.com/users/github-actions%5Bbot%5D/following{/other_user}",
        "gists_url": "https://api.github.com/users/github-actions%5Bbot%5D/gists{/gist_id}",
        "starred_url": "https://api.github.com/users/github-actions%5Bbot%5D/starred{/owner}{/repo}",
        "subscriptions_url": "https://api.github.com/users/github-actions%5Bbot%5D/subscriptions",
        "organizations_url": "https://api.github.com/users/github-actions%5Bbot%5D/orgs",
        "repos_url": "https://api.github.com/users/github-actions%5Bbot%5D/repos",
        "events_url": "https://api.github.com/users/github-actions%5Bbot%5D/events{/privacy}",
        "received_events_url": "https://api.github.com/users/github-actions%5Bbot%5D/received_events",
        "type": "Bot",
        "site_admin": false
      },
      "content_type": "binary/octet-stream",
      "state": "uploaded",
      "size": 58303742,
      "download_count": 0,
      "created_at": "2022-11-20T18:12:42Z",
      "updated_at": "2022-11-20T18:12:44Z",
      "browser_download_url": "https://github.com/Kingsmanvn-Official/Revanced-tool/releases/download/1/YT-Magisk-17.43.36-arm64.Zip"
    },
    {
      "url": "https://api.github.com/repos/Kingsmanvn-Official/Revanced-tool/releases/assets/85325609",
      "id": 85325609,
      "node_id": "RA_kwDOICdUDM4FFfcp",
      "name": "YT-NoRoot-17.43.36-arm64.Amoled.apk",
      "label": "",
      "uploader": {
        "login": "github-actions[bot]",
        "id": 41898282,
        "node_id": "MDM6Qm90NDE4OTgyODI=",
        "avatar_url": "https://avatars.githubusercontent.com/in/15368?v=4",
        "gravatar_id": "",
        "url": "https://api.github.com/users/github-actions%5Bbot%5D",
        "html_url": "https://github.com/apps/github-actions",
        "followers_url": "https://api.github.com/users/github-actions%5Bbot%5D/followers",
        "following_url": "https://api.github.com/users/github-actions%5Bbot%5D/following{/other_user}",
        "gists_url": "https://api.github.com/users/github-actions%5Bbot%5D/gists{/gist_id}",
        "starred_url": "https://api.github.com/users/github-actions%5Bbot%5D/starred{/owner}{/repo}",
        "subscriptions_url": "https://api.github.com/users/github-actions%5Bbot%5D/subscriptions",
        "organizations_url": "https://api.github.com/users/github-actions%5Bbot%5D/orgs",
        "repos_url": "https://api.github.com/users/github-actions%5Bbot%5D/repos",
        "events_url": "https://api.github.com/users/github-actions%5Bbot%5D/events{/privacy}",
        "received_events_url": "https://api.github.com/users/github-actions%5Bbot%5D/received_events",
        "type": "Bot",
        "site_admin": false
      },
      "content_type": "application/vnd.android.package-archive",
      "state": "uploaded",
      "size": 79321351,
      "download_count": 0,
      "created_at": "2022-11-20T18:12:53Z",
      "updated_at": "2022-11-20T18:12:55Z",
      "browser_download_url": "https://github.com/Kingsmanvn-Official/Revanced-tool/releases/download/1/YT-NoRoot-17.43.36-arm64.Amoled.apk"
    },
    {
      "url": "https://api.github.com/repos/Kingsmanvn-Official/Revanced-tool/releases/assets/85325695",
      "id": 85325695,
      "node_id": "RA_kwDOICdUDM4FFfd_",
      "name": "YT-NoRoot-17.43.36-arm64.apk",
      "label": "",
      "uploader": {
        "login": "github-actions[bot]",
        "id": 41898282,
        "node_id": "MDM6Qm90NDE4OTgyODI=",
        "avatar_url": "https://avatars.githubusercontent.com/in/15368?v=4",
        "gravatar_id": "",
        "url": "https://api.github.com/users/github-actions%5Bbot%5D",
        "html_url": "https://github.com/apps/github-actions",
        "followers_url": "https://api.github.com/users/github-actions%5Bbot%5D/followers",
        "following_url": "https://api.github.com/users/github-actions%5Bbot%5D/following{/other_user}",
        "gists_url": "https://api.github.com/users/github-actions%5Bbot%5D/gists{/gist_id}",
        "starred_url": "https://api.github.com/users/github-actions%5Bbot%5D/starred{/owner}{/repo}",
        "subscriptions_url": "https://api.github.com/users/github-actions%5Bbot%5D/subscriptions",
        "organizations_url": "https://api.github.com/users/github-actions%5Bbot%5D/orgs",
        "repos_url": "https://api.github.com/users/github-actions%5Bbot%5D/repos",
        "events_url": "https://api.github.com/users/github-actions%5Bbot%5D/events{/privacy}",
        "received_events_url": "https://api.github.com/users/github-actions%5Bbot%5D/received_events",
        "type": "Bot",
        "site_admin": false
      },
      "content_type": "application/vnd.android.package-archive",
      "state": "uploaded",
      "size": 79452423,
      "download_count": 0,
      "created_at": "2022-11-20T18:13:40Z",
      "updated_at": "2022-11-20T18:13:43Z",
      "browser_download_url": "https://github.com/Kingsmanvn-Official/Revanced-tool/releases/download/1/YT-NoRoot-17.43.36-arm64.apk"
    }
  ],
  "tarball_url": "https://api.github.com/repos/Kingsmanvn-Official/Revanced-tool/tarball/1",
  "zipball_url": "https://api.github.com/repos/Kingsmanvn-Official/Revanced-tool/zipball/1",
  "body": "2022-11-20\n  \nCLI: revanced-cli-2.16.0-all.jar  \n\nIntegrations: app-release-unsigned-v0.73.0.apk  \n\nPatches: revanced-patches-2.113.0.jar  \n[Patches Changelog](https://github.com/revanced/revanced-patches/releases/tag/v2.113.0)  \n\nYouTube version: 17.43.36\n\nUse [MicroG APK](https://github.com/inotia00/VancedMicroG/releases/latest/download/microg.apk) for YouTube and Music\n\n[Revanced-tool repo](https://github.com/Kingsmanvn-Official/Revanced-tool)"
}
